{
  "project_info": {
    "project_number": "401368738928",
    "firebase_url": "https://youoweme-6c622.firebaseio.com",
    "project_id": "youoweme-6c622",
    "storage_bucket": "youoweme-6c622.appspot.com"
  },
  "client": [
    {
      "client_info": {
        "mobilesdk_app_id": "1:401368738928:android:547df5812c0305cc0958b5",
        "android_client_info": {
          "package_name": "dev.preetjdp.youoweme"
        }
      },
      "oauth_client": [
        {
          "client_id": "401368738928-otf7mn29qmv3ctk51ogth53ltgn7hf47.apps.googleusercontent.com",
          "client_type": 1,
          "android_info": {
            "package_name": "dev.preetjdp.youoweme",
            "certificate_hash": "7b07940e2eb99be5290b99421bd0363cd5438b30"
          }
        },
        {
          "client_id": "401368738928-224rt3nfqspq9p61mdibl7gdb6npjjs8.apps.googleusercontent.com",
          "client_type": 1,
          "android_info": {
            "package_name": "dev.preetjdp.youoweme",
            "certificate_hash": "f9d0996a913080be00599af384342b5092a0108e"
          }
        },
        {
          "client_id": "401368738928-abmkcd6ulatb39tbn2nm7b8ntk0h8kpe.apps.googleusercontent.com",
          "client_type": 1,
          "android_info": {
            "package_name": "dev.preetjdp.youoweme",
            "certificate_hash": "0f17a8693a25871038f5653a95a7e7f316c27ba9"
          }
        },
        {
          "client_id": "401368738928-k4v46nvvhm67qtess1anuggqu5f3ocn9.apps.googleusercontent.com",
          "client_type": 1,
          "android_info": {
            "package_name": "dev.preetjdp.youoweme",
            "certificate_hash": "35d6edcc540c37e843e3131572c7d24eba082c3b"
          }
        },
        {
          "client_id": "401368738928-e11u3pg7v2ngrv7fvo3m242361ih5n8v.apps.googleusercontent.com",
          "client_type": 3
        }
      ],
      "api_key": [
        {
          "current_key": "AIzaSyBWK6dGIPu0CVrm96T4eOsFLH2mgJt4Uf0"
        }
      ],
      "services": {
        "appinvite_service": {
          "other_platform_oauth_client": [
            {
              "client_id": "401368738928-e11u3pg7v2ngrv7fvo3m242361ih5n8v.apps.googleusercontent.com",
              "client_type": 3
            },
            {
              "client_id": "401368738928-9eavhn0fflpq3pcd2148g2bdtt5o9mlg.apps.googleusercontent.com",
              "client_type": 2,
              "ios_info": {
                "bundle_id": "dev.preetjdp.youoweme"
              }
            }
          ]
        }
      }
    }
  ],
  "configuration_version": "1"
}